-- BYTECODE -- "voicesynth":0-0
0001    ISF          0
0002    JMP      1 => 0049
0003    TGETS    1   0   0  ; "count"
0004    IST          1
0005    JMP      2 => 0007
0006    KSHORT   1   1
0007 => TGETS    2   0   0  ; "count"
0008    ISF          2
0009    JMP      3 => 0012
0010    KSHORT   2   1
0011    JMP      3 => 0020
0012 => GGET     2   1      ; "bit"
0013    TGETS    2   2   2  ; "band"
0014    TGETS    3   0   3  ; "typ"
0015    IST          3
0016    JMP      4 => 0018
0017    KSHORT   3   0
0018 => KSHORT   4   1
0019    CALL     2   2   3
0020 => UGET     3   0      ; 
0021    TGETS    4   0   4  ; "data"
0022    MOV      5   2
0023    TGETS    6   0   5  ; "phonecount"
0024    TGETS    7   0   6  ; "phoneorder"
0025    CALL     3   1   5
0026    KSHORT   3   2
0027    SUBVN    4   1   0  ; 1
0028    KSHORT   5   1
0029    FORI     3 => 0041
0030 => UGET     7   1      ; 
0031    TGETS    8   0   4  ; "data"
0032    TGETS    9   0   7  ; "data2"
0033    MOV     10   1
0034    SUBVN   11   6   0  ; 1
0035    CALL     7   2   5
0036    UGET     8   0      ; 
0037    MOV      9   7
0038    MOV     10   2
0039    CALL     8   1   3
0040    FORL     3 => 0030
0041 => KSHORT   3   1
0042    ISGE     3   1
0043    JMP      3 => 0051
0044    UGET     3   0      ; 
0045    TGETS    4   0   7  ; "data2"
0046    MOV      5   2
0047    CALL     3   1   3
0048    JMP      1 => 0051
0049 => UGET     1   0      ; 
0050    CALL     1   1   1
0051 => RET0     0   1

