-- BYTECODE -- "translate":0-0
0001    LEN      1   0
0002    DIVVN    1   1   0  ; 2
0003    KSHORT   2   1
0004    MOV      3   1
0005    TNEW     4   0
0006 => ISGT     2   3
0007    JMP      5 => 0122
0008    LOOP     5 => 0122
0009    SUBVV    5   1   3
0010    KNIL     6  10
0011    SUBVN   11   2   1  ; 1
0012    MULVN   11  11   0  ; 2
0013    ADDVN   11  11   1  ; 1
0014    SUBVN   12   3   1  ; 1
0015    MULVN   12  12   0  ; 2
0016    ADDVN   12  12   0  ; 2
0017    ADDVN   13   5   1  ; 1
0018    ISGE    13   1
0019    JMP     13 => 0041
0020    KSTR    13   0      ; "N\000+\000"
0021    MOV     15   0
0022    TGETS   14   0   1  ; "sub"
0023    MOV     16  11
0024    MOV     17  12
0025    CALL    14   2   4
0026    KSTR    15   2      ; "+\000"
0027    MOV     16   5
0028    UGET    17   0      ; 
0029    KSTR    18   3      ; "R\000"
0030    CAT      6  13  18
0031    KSTR    13   0      ; "N\000+\000"
0032    MOV     15   0
0033    TGETS   14   0   1  ; "sub"
0034    MOV     16  11
0035    MOV     17  12
0036    CALL    14   2   4
0037    KSTR    15   2      ; "+\000"
0038    MOV     16   5
0039    UGET    17   0      ; 
0040    CAT      7  13  17
0041 => KSTR    13   4      ; "N\000"
0042    MOV     15   0
0043    TGETS   14   0   1  ; "sub"
0044    MOV     16  11
0045    MOV     17  12
0046    CALL    14   2   4
0047    KSTR    15   2      ; "+\000"
0048    MOV     16   5
0049    UGET    17   0      ; 
0050    KSTR    18   3      ; "R\000"
0051    CAT      8  13  18
0052    KSTR    13   4      ; "N\000"
0053    MOV     15   0
0054    TGETS   14   0   1  ; "sub"
0055    MOV     16  11
0056    MOV     17  12
0057    CALL    14   2   4
0058    KSTR    15   2      ; "+\000"
0059    MOV     16   5
0060    UGET    17   0      ; 
0061    CAT      9  13  17
0062    ISF          6
0063    JMP     13 => 0068
0064    UGET    13   1      ; 
0065    TGETV   13  13   6
0066    IST         13
0067    JMP     14 => 0090
0068 => ISF          7
0069    JMP     13 => 0074
0070    UGET    13   1      ; 
0071    TGETV   13  13   7
0072    IST         13
0073    JMP     14 => 0090
0074 => ISF          8
0075    JMP     13 => 0080
0076    UGET    13   1      ; 
0077    TGETV   13  13   8
0078    IST         13
0079    JMP     14 => 0090
0080 => ISF          9
0081    JMP     13 => 0086
0082    UGET    13   1      ; 
0083    TGETV   13  13   9
0084    IST         13
0085    JMP     14 => 0090
0086 => ISFC    13  10
0087    JMP     13 => 0090
0088    UGET    13   1      ; 
0089    TGETV   13  13  10
0090 => ISF         13
0091    JMP     14 => 0113
0092    TSETV   13   4   2
0093    IST          6
0094    JMP     14 => 0097
0095    ISF          8
0096    JMP     14 => 0107
0097 => ADDVN   14   2   1  ; 1
0098    MOV     15   1
0099    KSHORT  16   1
0100    FORI    14 => 0107
0101 => TGETV   18   4  17
0102    IST         18
0103    JMP     19 => 0105
0104    KPRI    18   2
0105 => TSETV   18   4  17
0106    FORL    14 => 0101
0107 => SUBVN    3   2   1  ; 1
0108    ISNEN    3   2      ; 0
0109    JMP     14 => 0111
0110    JMP      5 => 0122
0111 => KSHORT   2   1
0112    JMP     14 => 0006
0113 => ADDVN    2   2   1  ; 1
0114    ISGE     3   2
0115    JMP     14 => 0006
0116    SUBVN    3   3   1  ; 1
0117    ISNEN    3   2      ; 0
0118    JMP     14 => 0120
0119    JMP      5 => 0122
0120 => KSHORT   2   1
0121    JMP      5 => 0006
0122 => KSHORT   5   1
0123    MOV      6   1
0124    KSHORT   7   1
0125    FORI     5 => 0146
0126 => SUBVN    9   8   1  ; 1
0127    MULVN    9   9   0  ; 2
0128    ADDVN    9   9   1  ; 1
0129    TGETV   10   4   8
0130    IST         10
0131    JMP     10 => 0143
0132    UGET    10   1      ; 
0133    KSTR    11   4      ; "N\000"
0134    MOV     13   0
0135    TGETS   12   0   1  ; "sub"
0136    MOV     14   9
0137    ADDVN   15   9   1  ; 1
0138    CALL    12   2   4
0139    CAT     11  11  12
0140    TGETV   10  10  11
0141    IST         10
0142    JMP     11 => 0144
0143 => TGETV   10   4   8
0144 => TSETV   10   4   8
0145    FORL     5 => 0126
0146 => TNEW     5   0
0147    KSHORT   6   1
0148    MOV      7   1
0149    KSHORT   8   1
0150    FORI     6 => 0168
0151 => GGET    10   5      ; "type"
0152    TGETV   11   4   9
0153    CALL    10   2   2
0154    ISNES   10   6      ; "table"
0155    JMP     10 => 0167
0156    KSHORT  10   1
0157    TGETV   11   4   9
0158    LEN     11  11
0159    KSHORT  12   1
0160    FORI    10 => 0167
0161 => LEN     14   5
0162    ADDVN   14  14   1  ; 1
0163    TGETV   15   4   9
0164    TGETV   15  15  13
0165    TSETV   15   5  14
0166    FORL    10 => 0161
0167 => FORL     6 => 0151
0168 => GGET     6   7      ; "unpack"
0169    MOV      7   5
0170    CALLT    6   2

